setup.py
mukhina_123/__init__.py
mukhina_123/one.py
mukhina_123/two.py
mukhina_123.egg-info/PKG-INFO
mukhina_123.egg-info/SOURCES.txt
mukhina_123.egg-info/dependency_links.txt
mukhina_123.egg-info/top_level.txt