Metadata-Version: 2.1
Name: mukhina-123
Version: 0.0.1
Summary: My pack
Author: Anna
Author-email: a.mukhina@gmail.com
